<?xml version="1.0" encoding="UTF-8"?><record_update table="sp_container">
    <sp_container action="INSERT_OR_UPDATE">
        <background_color/>
        <background_image/>
        <background_style>default</background_style>
        <bootstrap_alt>false</bootstrap_alt>
        <class_name/>
        <container_class_name/>
        <name>Coworkers from the same group - Container 1</name>
        <order>1</order>
        <semantic_tag/>
        <sp_page display_value="petrux_groups">fdc99e2c83cfd2108672e480ceaad334</sp_page>
        <subheader>false</subheader>
        <sys_class_name>sp_container</sys_class_name>
        <sys_created_by>admin</sys_created_by>
        <sys_created_on>2025-01-09 04:16:02</sys_created_on>
        <sys_id>39c99e2c83cfd2108672e480ceaad338</sys_id>
        <sys_mod_count>1</sys_mod_count>
        <sys_name>Coworkers from the same group - Container 1</sys_name>
        <sys_package display_value="PetruX" source="x_558714_petrux">bce60b0c830f52108672e480ceaad35e</sys_package>
        <sys_policy/>
        <sys_scope display_value="PetruX">bce60b0c830f52108672e480ceaad35e</sys_scope>
        <sys_update_name>sp_container_39c99e2c83cfd2108672e480ceaad338</sys_update_name>
        <sys_updated_by>admin</sys_updated_by>
        <sys_updated_on>2025-01-09 04:36:16</sys_updated_on>
        <title/>
        <width>container</width>
    </sp_container>
</record_update>
